cfssl_cli/__init__.py
cfssl_cli/__main__.py
cfssl_cli/__version__.py
cfssl_cli/checksums.py
cfssl_cli/config/config.yml
cfssl_cli/configuration.py
cfssl_cli/crypto.py
cfssl_cli/test/test_checksums.py
cfssl_cli/test/test_configuration.py
cfssl_cli/test/test_crypto.py
cfssl_cli/test/test_writer.py
cfssl_cli/writer.py
cfssl_cli-1.4.0.dist-info/entry_points.txt
cfssl_cli-1.4.0.dist-info/LICENSE
cfssl_cli-1.4.0.dist-info/WHEEL
cfssl_cli-1.4.0.dist-info/METADATA
cfssl_cli-1.4.0.dist-info/RECORD
