Metadata-Version: 2.1
Name: cfssl-cli
Version: 1.4.0
Summary: This CLI tool allows you to generate certificates from a remote CFSSL server.
Home-page: https://github.com/Toilal/python-cfssl-cli
License: MIT
Keywords: cfssl,ssl,certificate,certificates,cli
Author: Rémi Alvergnat
Author-email: toilal.dev@gmail.com
Requires-Python: >=3.6,<4.0
Classifier: Development Status :: 5 - Production/Stable
Classifier: Environment :: Console
Classifier: Intended Audience :: Developers
Classifier: Intended Audience :: System Administrators
Classifier: License :: OSI Approved :: MIT License
Classifier: Programming Language :: Python
Classifier: Programming Language :: Python :: 3
Classifier: Programming Language :: Python :: 3.6
Classifier: Programming Language :: Python :: 3.7
Classifier: Programming Language :: Python :: 3.8
Classifier: Programming Language :: Python :: 3.9
Classifier: Topic :: Security
Classifier: Topic :: System :: Networking
Requires-Dist: PyYAML (>=5.4.1,<6.0.0)
Requires-Dist: cfssl (>=0.0.3-beta.243,<0.0.4)
Requires-Dist: click (>=7.1.2,<8.0.0)
Requires-Dist: cryptography (>=3.4.7,<4.0.0)
Project-URL: Documentation, https://github.com/Toilal/python-cfssl-cli
Project-URL: Repository, https://github.com/Toilal/python-cfssl-cli
